ezconfig/__init__.py
ezconfig/config.py
ezconfig-1.9.1.dist-info/METADATA
ezconfig-1.9.1.dist-info/WHEEL
ezconfig-1.9.1.dist-info/licenses/LICENSE.txt
ezconfig-1.9.1.dist-info/RECORD
