Metadata-Version: 2.4
Name: ezconfig
Version: 1.9.1
License-File: LICENSE.txt
Requires-Python: >=3.9
Requires-Dist: python-dateutil
Provides-Extra: dev
Requires-Dist: build>=0.7.0; extra == 'dev'
Requires-Dist: emacsipython; extra == 'dev'
Requires-Dist: ipython; extra == 'dev'
Requires-Dist: mypy>=1.0.0; extra == 'dev'
Requires-Dist: pre-commit>=3.0.0; extra == 'dev'
Requires-Dist: pytest-cov>=4.0.0; extra == 'dev'
Requires-Dist: pytest>=7.0.0; extra == 'dev'
Requires-Dist: ruff>=0.1.0; extra == 'dev'
Requires-Dist: sphinx; extra == 'dev'
Requires-Dist: sphinx-autobuild; extra == 'dev'
Requires-Dist: twine>=4.0.0; extra == 'dev'
Provides-Extra: test
Requires-Dist: pytest-cov>=4.0.0; extra == 'test'
Requires-Dist: pytest>=7.0.0; extra == 'test'
